Outliers/Outliers_file.py
Outliers_101703319-1.0.2.dist-info/LICENSE.txt
Outliers_101703319-1.0.2.dist-info/METADATA
Outliers_101703319-1.0.2.dist-info/WHEEL
Outliers_101703319-1.0.2.dist-info/entry_points.txt
Outliers_101703319-1.0.2.dist-info/top_level.txt
Outliers_101703319-1.0.2.dist-info/RECORD
